ipysimulate/__init__.py
ipysimulate/_version.py
ipysimulate/charts.py
ipysimulate/control.py
ipysimulate/parameters.py
ipysimulate/simulation.py
ipysimulate/tools.py
ipysimulate/labextension/package.json
ipysimulate/labextension/static/261.bf480c12a62f6cddaae6.js
ipysimulate/labextension/static/486.9f3083af0b6c0150ab99.js
ipysimulate/labextension/static/486.9f3083af0b6c0150ab99.js.LICENSE.txt
ipysimulate/labextension/static/568.381891e86463acdbd8ea.js
ipysimulate/labextension/static/927.1486d759110a35701d91.js
ipysimulate/labextension/static/remoteEntry.3bc023fa27119d0f737f.js
ipysimulate/labextension/static/style.js
ipysimulate/nbextension/extension.js
ipysimulate/nbextension/index.js
ipysimulate/nbextension/index.js.LICENSE.txt
ipysimulate-0.2.1.data/data/etc/jupyter/nbconfig/notebook.d/ipysimulate.json
ipysimulate-0.2.1.data/data/share/jupyter/labextensions/ipysimulate/install.json
ipysimulate-0.2.1.data/data/share/jupyter/labextensions/ipysimulate/package.json
ipysimulate-0.2.1.data/data/share/jupyter/labextensions/ipysimulate/static/261.bf480c12a62f6cddaae6.js
ipysimulate-0.2.1.data/data/share/jupyter/labextensions/ipysimulate/static/486.9f3083af0b6c0150ab99.js
ipysimulate-0.2.1.data/data/share/jupyter/labextensions/ipysimulate/static/486.9f3083af0b6c0150ab99.js.LICENSE.txt
ipysimulate-0.2.1.data/data/share/jupyter/labextensions/ipysimulate/static/568.381891e86463acdbd8ea.js
ipysimulate-0.2.1.data/data/share/jupyter/labextensions/ipysimulate/static/927.1486d759110a35701d91.js
ipysimulate-0.2.1.data/data/share/jupyter/labextensions/ipysimulate/static/remoteEntry.3bc023fa27119d0f737f.js
ipysimulate-0.2.1.data/data/share/jupyter/labextensions/ipysimulate/static/style.js
ipysimulate-0.2.1.data/data/share/jupyter/nbextensions/ipysimulate/extension.js
ipysimulate-0.2.1.data/data/share/jupyter/nbextensions/ipysimulate/index.js
ipysimulate-0.2.1.data/data/share/jupyter/nbextensions/ipysimulate/index.js.LICENSE.txt
ipysimulate-0.2.1.dist-info/LICENSE
ipysimulate-0.2.1.dist-info/METADATA
ipysimulate-0.2.1.dist-info/WHEEL
ipysimulate-0.2.1.dist-info/top_level.txt
ipysimulate-0.2.1.dist-info/RECORD
