Metadata-Version: 2.1
Name: ipysimulate
Version: 0.2.1
Summary: Tools to create interactive simulations with IPython and Jupyter.
Home-page: https://github.com/JoelForamitti/ipysimulate
Author: Joël Foramitti
Author-email: joel.foramitti@uab.cat
License: UNKNOWN
Keywords: ipython,jupyter,widgets
Platform: UNKNOWN
Classifier: Development Status :: 4 - Beta
Classifier: Framework :: IPython
Classifier: Intended Audience :: Developers
Classifier: Intended Audience :: Science/Research
Classifier: Topic :: Multimedia :: Graphics
Classifier: Programming Language :: Python :: 3.6
Classifier: Programming Language :: Python :: 3.7
Classifier: Programming Language :: Python :: 3.8
Classifier: Programming Language :: Python :: 3.9
Requires-Dist: ipywidgets (>=7.6.0)
Provides-Extra: docs
Requires-Dist: sphinx (>=3.2.1) ; extra == 'docs'
Requires-Dist: nbsphinx (>=0.7.1) ; extra == 'docs'
Requires-Dist: sphinx-rtd-theme (>=0.4.3) ; extra == 'docs'
